rstmarcutree/__init__.py
rstmarcutree/classes.py
rstmarcutree/rstmarcutree.py
rstmarcutree-1.0.7.dist-info/METADATA
rstmarcutree-1.0.7.dist-info/WHEEL
rstmarcutree-1.0.7.dist-info/top_level.txt
rstmarcutree-1.0.7.dist-info/RECORD
