Metadata-Version: 2.1
Name: rstmarcutree
Version: 1.0.7
Summary: A project to load rst discourse tree enriched with Marcu attribute from .dis files
Home-page: https://github.com/Christian-Nja/rstmarcutree
Author: Christian Colonna
Author-email: christian.colonna@studio.unibo.it
License: BSD
Platform: UNKNOWN
Classifier: Development Status :: 3 - Alpha
Classifier: Intended Audience :: Developers
Classifier: Topic :: Software Development :: Build Tools
Classifier: License :: OSI Approved :: BSD License
Classifier: Programming Language :: Python :: 2.7
